{"namedChunkGroups":{"polyfill":{"name":"polyfill","assets":[{"name":"webpack-runtime-4bfa7087349bb613408d.js","size":5544},{"name":"polyfill-b43dc1a2473cda01c5e4.js","size":82631}],"filteredAssets":0,"assetsSize":88175,"filteredAuxiliaryAssets":2,"auxiliaryAssetsSize":222369},"app":{"name":"app","assets":[{"name":"webpack-runtime-4bfa7087349bb613408d.js","size":5544},{"name":"framework-390de80c595a12267f69.js","size":128959},{"name":"app-f1ee0ab2e8baee8b3f66.js","size":90436}],"filteredAssets":0,"assetsSize":224939,"filteredAuxiliaryAssets":3,"auxiliaryAssetsSize":768651},"component---src-pages-404-js":{"name":"component---src-pages-404-js","assets":[{"name":"styles.e7189ed0bb994cc11806.css","size":110621},{"name":"cb1608f2-dbff4bf6d324a491e0c4.js","size":1206},{"name":"a9a7754c-77c00022c02b7ea9765e.js","size":465895},{"name":"commons-23d32b5c1c755c5d7a8a.js","size":202955},{"name":"component---src-pages-404-js-bfa6846b9f0daa84aa1d.js","size":486}],"filteredAssets":0,"assetsSize":781163,"filteredAuxiliaryAssets":20,"auxiliaryAssetsSize":5177503},"component---src-pages-contentboard-js":{"name":"component---src-pages-contentboard-js","assets":[{"name":"styles.e7189ed0bb994cc11806.css","size":110621},{"name":"cb1608f2-dbff4bf6d324a491e0c4.js","size":1206},{"name":"a9a7754c-77c00022c02b7ea9765e.js","size":465895},{"name":"ea88be26-a64313338bb061c29509.js","size":265878},{"name":"commons-23d32b5c1c755c5d7a8a.js","size":202955},{"name":"component---src-pages-contentboard-js-5f876bc967b8eb839815.js","size":230134}],"filteredAssets":0,"assetsSize":1276689,"filteredAuxiliaryAssets":25,"auxiliaryAssetsSize":6507665},"component---src-pages-datenschutz-js":{"name":"component---src-pages-datenschutz-js","assets":[{"name":"styles.e7189ed0bb994cc11806.css","size":110621},{"name":"cb1608f2-dbff4bf6d324a491e0c4.js","size":1206},{"name":"a9a7754c-77c00022c02b7ea9765e.js","size":465895},{"name":"commons-23d32b5c1c755c5d7a8a.js","size":202955},{"name":"component---src-pages-datenschutz-js-b83dc272653dceea39f9.js","size":15855}],"filteredAssets":0,"assetsSize":796532,"filteredAuxiliaryAssets":20,"auxiliaryAssetsSize":5198249},"component---src-pages-elements-js":{"name":"component---src-pages-elements-js","assets":[{"name":"styles.e7189ed0bb994cc11806.css","size":110621},{"name":"cb1608f2-dbff4bf6d324a491e0c4.js","size":1206},{"name":"a9a7754c-77c00022c02b7ea9765e.js","size":465895},{"name":"commons-23d32b5c1c755c5d7a8a.js","size":202955},{"name":"component---src-pages-elements-js-b031a8b23bed917e667b.js","size":30988}],"filteredAssets":0,"assetsSize":811665,"filteredAuxiliaryAssets":25,"auxiliaryAssetsSize":5963675},"component---src-pages-generic-js":{"name":"component---src-pages-generic-js","assets":[{"name":"styles.e7189ed0bb994cc11806.css","size":110621},{"name":"cb1608f2-dbff4bf6d324a491e0c4.js","size":1206},{"name":"a9a7754c-77c00022c02b7ea9765e.js","size":465895},{"name":"commons-23d32b5c1c755c5d7a8a.js","size":202955},{"name":"component---src-pages-generic-js-5d054d6e63e532d223cd.js","size":3065}],"filteredAssets":0,"assetsSize":783742,"filteredAuxiliaryAssets":20,"auxiliaryAssetsSize":5180620},"component---src-pages-impressum-js":{"name":"component---src-pages-impressum-js","assets":[{"name":"styles.e7189ed0bb994cc11806.css","size":110621},{"name":"cb1608f2-dbff4bf6d324a491e0c4.js","size":1206},{"name":"a9a7754c-77c00022c02b7ea9765e.js","size":465895},{"name":"commons-23d32b5c1c755c5d7a8a.js","size":202955},{"name":"component---src-pages-impressum-js-a3d8d1eeda5740fee53c.js","size":1365}],"filteredAssets":0,"assetsSize":782042,"filteredAuxiliaryAssets":20,"auxiliaryAssetsSize":5178629},"component---src-pages-index-js":{"name":"component---src-pages-index-js","assets":[{"name":"styles.e7189ed0bb994cc11806.css","size":110621},{"name":"cb1608f2-dbff4bf6d324a491e0c4.js","size":1206},{"name":"a9a7754c-77c00022c02b7ea9765e.js","size":465895},{"name":"commons-23d32b5c1c755c5d7a8a.js","size":202955},{"name":"component---src-pages-index-js-7078db43d0024c7acfa3.js","size":306035}],"filteredAssets":0,"assetsSize":1086712,"filteredAuxiliaryAssets":26,"auxiliaryAssetsSize":7145247},"component---src-pages-kontakt-js":{"name":"component---src-pages-kontakt-js","assets":[{"name":"styles.e7189ed0bb994cc11806.css","size":110621},{"name":"cb1608f2-dbff4bf6d324a491e0c4.js","size":1206},{"name":"a9a7754c-77c00022c02b7ea9765e.js","size":465895},{"name":"commons-23d32b5c1c755c5d7a8a.js","size":202955},{"name":"component---src-pages-kontakt-js-acc1fb5424d23974763f.js","size":3015}],"filteredAssets":0,"assetsSize":783692,"filteredAuxiliaryAssets":20,"auxiliaryAssetsSize":5183858}},"assetsByChunkName":{"polyfill":["webpack-runtime-4bfa7087349bb613408d.js","polyfill-b43dc1a2473cda01c5e4.js"],"app":["webpack-runtime-4bfa7087349bb613408d.js","framework-390de80c595a12267f69.js","app-f1ee0ab2e8baee8b3f66.js"],"component---src-pages-404-js":["styles.e7189ed0bb994cc11806.css","cb1608f2-dbff4bf6d324a491e0c4.js","a9a7754c-77c00022c02b7ea9765e.js","commons-23d32b5c1c755c5d7a8a.js","component---src-pages-404-js-bfa6846b9f0daa84aa1d.js"],"component---src-pages-contentboard-js":["styles.e7189ed0bb994cc11806.css","cb1608f2-dbff4bf6d324a491e0c4.js","a9a7754c-77c00022c02b7ea9765e.js","ea88be26-a64313338bb061c29509.js","commons-23d32b5c1c755c5d7a8a.js","component---src-pages-contentboard-js-5f876bc967b8eb839815.js"],"component---src-pages-datenschutz-js":["styles.e7189ed0bb994cc11806.css","cb1608f2-dbff4bf6d324a491e0c4.js","a9a7754c-77c00022c02b7ea9765e.js","commons-23d32b5c1c755c5d7a8a.js","component---src-pages-datenschutz-js-b83dc272653dceea39f9.js"],"component---src-pages-elements-js":["styles.e7189ed0bb994cc11806.css","cb1608f2-dbff4bf6d324a491e0c4.js","a9a7754c-77c00022c02b7ea9765e.js","commons-23d32b5c1c755c5d7a8a.js","component---src-pages-elements-js-b031a8b23bed917e667b.js"],"component---src-pages-generic-js":["styles.e7189ed0bb994cc11806.css","cb1608f2-dbff4bf6d324a491e0c4.js","a9a7754c-77c00022c02b7ea9765e.js","commons-23d32b5c1c755c5d7a8a.js","component---src-pages-generic-js-5d054d6e63e532d223cd.js"],"component---src-pages-impressum-js":["styles.e7189ed0bb994cc11806.css","cb1608f2-dbff4bf6d324a491e0c4.js","a9a7754c-77c00022c02b7ea9765e.js","commons-23d32b5c1c755c5d7a8a.js","component---src-pages-impressum-js-a3d8d1eeda5740fee53c.js"],"component---src-pages-index-js":["styles.e7189ed0bb994cc11806.css","cb1608f2-dbff4bf6d324a491e0c4.js","a9a7754c-77c00022c02b7ea9765e.js","commons-23d32b5c1c755c5d7a8a.js","component---src-pages-index-js-7078db43d0024c7acfa3.js"],"component---src-pages-kontakt-js":["styles.e7189ed0bb994cc11806.css","cb1608f2-dbff4bf6d324a491e0c4.js","a9a7754c-77c00022c02b7ea9765e.js","commons-23d32b5c1c755c5d7a8a.js","component---src-pages-kontakt-js-acc1fb5424d23974763f.js"]},"childAssetsByChunkName":{}}